ito/__init__.py
ito/itolib.py
ito/itosdk.py
ito/libitosdk.dll
ito/libitosdk.so
ito-0.0.2.dist-info/LICENSE
ito-0.0.2.dist-info/METADATA
ito-0.0.2.dist-info/WHEEL
ito-0.0.2.dist-info/top_level.txt
ito-0.0.2.dist-info/RECORD
