Metadata-Version: 2.1
Name: ito
Version: 0.0.2
Summary: A domain specific language for the description of financial derivatives.
Home-page: https://github.com/rexsutton/vollab
Author: Rex Sutton
Author-email: noreply@nospam.com
License: UNKNOWN
Project-URL: Bug Tracker, https://github.com/rexsutton/vollab/issues
Platform: UNKNOWN
Classifier: Programming Language :: Python :: 3
Classifier: License :: OSI Approved :: BSD License
Classifier: Operating System :: OS Independent
Requires-Python: >=3.6
